devnotes/__init__.py
devnotes/admin.py
devnotes/apps.py
devnotes/forms.py
devnotes/middleware.py
devnotes/models.py
devnotes/tests.py
devnotes/urls.py
devnotes/views.py
devnotes/migrations/0001_initial.py
devnotes/migrations/0002_devnote_completed_at.py
devnotes/migrations/0003_devnote_name.py
devnotes/migrations/__init__.py
devnotes/static/devnotes/css/devnote.css
devnotes/static/devnotes/js/jquery.min.js
devnotes/templates/devnotes/add-note.html
devnotes/templates/devnotes/index.html
devnotes/templates/devnotes/list.html
django_devnotes-0.2.dist-info/LICENSE
django_devnotes-0.2.dist-info/METADATA
django_devnotes-0.2.dist-info/WHEEL
django_devnotes-0.2.dist-info/top_level.txt
django_devnotes-0.2.dist-info/RECORD
