Metadata-Version: 2.1
Name: django-devnotes
Version: 0.2
Summary: Devnotes is a simple Django app to store handy notes alongside your project
Home-page: https://github.com/bsurajbh/django-devnotes
Author: Suraj Bhadange
Author-email: 
License: MIT License
Platform: UNKNOWN
Classifier: Programming Language :: Python :: 3
Classifier: License :: OSI Approved :: MIT License
Classifier: Operating System :: OS Independent
Requires-Python: >=3.6
